segment_reshape/__init__.py
segment_reshape/py.typed
segment_reshape/geometry/__init__.py
segment_reshape/geometry/reshape.py
segment_reshape/map_tool/__init__.py
segment_reshape/map_tool/segment_reshape_tool.py
segment_reshape/topology/__init__.py
segment_reshape/topology/find_related.py
segment_reshape/utils/__init__.py
segment_reshape/utils/geometry_utils.py
segment_reshape_plugin/__init__.py
segment_reshape_plugin/metadata.txt
segment_reshape_plugin/plugin.py
segment_reshape_plugin/py.typed
segment_reshape_plugin/resources/i18n/fi.ts
segment_reshape_plugin/resources/icons/segment_reshape.svg
segment_reshape_qgis_plugin-0.1.10.dist-info/licenses/LICENSE
segment_reshape_qgis_plugin-0.1.10.dist-info/METADATA
segment_reshape_qgis_plugin-0.1.10.dist-info/WHEEL
segment_reshape_qgis_plugin-0.1.10.dist-info/entry_points.txt
segment_reshape_qgis_plugin-0.1.10.dist-info/top_level.txt
segment_reshape_qgis_plugin-0.1.10.dist-info/RECORD
