Metadata-Version: 2.4
Name: segment-reshape-qgis-plugin
Version: 0.1.10
Summary: QGIS plugin with a map tool to reshape a continuous segment topogically.
Home-page: https://github.com/nlsfi/segment-reshape-qgis-plugin
Author: National Land Survey of Finland
Author-email: os@nls.fi
License: GNU GPL v3.0
Project-URL: Changelog, https://github.com/nlsfi/segment-reshape-qgis-plugin/blob/main/CHANGELOG.md
Keywords: qgis
Classifier: Development Status :: 3 - Alpha
Classifier: License :: OSI Approved :: GNU General Public License v3 (GPLv3)
Classifier: Operating System :: OS Independent
Classifier: Programming Language :: Python :: 3 :: Only
Classifier: Programming Language :: Python :: Implementation :: CPython
Classifier: Topic :: Software Development :: Libraries
Classifier: Typing :: Typed
License-File: LICENSE
Requires-Dist: qgis_plugin_tools>=0.2.0
Dynamic: license-file
